{
  "/_global-error/page": "app/_global-error/page.js",
  "/_not-found/page": "app/_not-found/page.js",
  "/analyze/page": "app/analyze/page.js",
  "/api/auth/complete-profile/route": "app/api/auth/complete-profile/route.js",
  "/api/auth/send-email-otp/route": "app/api/auth/send-email-otp/route.js",
  "/api/auth/send-sms/route": "app/api/auth/send-sms/route.js",
  "/api/auth/sync/route": "app/api/auth/sync/route.js",
  "/api/auth/verify-email-otp/route": "app/api/auth/verify-email-otp/route.js",
  "/api/auth/verify-phone/route": "app/api/auth/verify-phone/route.js",
  "/api/chat-session/route": "app/api/chat-session/route.js",
  "/api/chat/route": "app/api/chat/route.js",
  "/api/dify-chat/route": "app-edge-has-no-entrypoint",
  "/api/dify-upload/route": "app/api/dify-upload/route.js",
  "/api/document-process/route": "app/api/document-process/route.js",
  "/api/essay-grade/route": "app/api/essay-grade/route.js",
  "/api/essay-review/route": "app/api/essay-review/route.js",
  "/api/ocr/route": "app-edge-has-no-entrypoint",
  "/api/payment/status/[orderNo]/route": "app/api/payment/status/[orderNo]/route.js",
  "/api/payment/xunhupay/create/route": "app/api/payment/xunhupay/create/route.js",
  "/api/payment/xunhupay/notify/route": "app/api/payment/xunhupay/notify/route.js",
  "/api/presentation/route": "app/api/presentation/route.js",
  "/api/providers/route": "app/api/providers/route.js",
  "/api/referral/process/route": "app/api/referral/process/route.js",
  "/api/save-essay-review/route": "app/api/save-essay-review/route.js",
  "/api/save-message/route": "app/api/save-message/route.js",
  "/api/sparkpage/route": "app/api/sparkpage/route.js",
  "/api/user/credits/route": "app/api/user/credits/route.js",
  "/api/user/update/route": "app-edge-has-no-entrypoint",
  "/api/web-search/route": "app/api/web-search/route.js",
  "/auth/callback/route": "app/auth/callback/route.js",
  "/auth/complete-profile/page": "app/auth/complete-profile/page.js",
  "/auth/confirm/route": "app/auth/confirm/route.js",
  "/auth/email-login/page": "app/auth/email-login/page.js",
  "/auth/error/page": "app/auth/error/page.js",
  "/auth/login/page": "app/auth/login/page.js",
  "/auth/phone-login/page": "app/auth/phone-login/page.js",
  "/auth/sign-up-success/page": "app/auth/sign-up-success/page.js",
  "/auth/sign-up/page": "app/auth/sign-up/page.js",
  "/auth/wechat-login/page": "app/auth/wechat-login/page.js",
  "/chat/page": "app/chat/page.js",
  "/checkout/[productId]/page": "app/checkout/[productId]/page.js",
  "/credits/page": "app/credits/page.js",
  "/essay/page": "app/essay/page.js",
  "/history/page": "app/history/page.js",
  "/login/page": "app/login/page.js",
  "/page": "app/page.js",
  "/parent/page": "app/parent/page.js",
  "/payment/success/page": "app/payment/success/page.js",
  "/payment/wechat/[orderNo]/page": "app/payment/wechat/[orderNo]/page.js",
  "/pricing/page": "app/pricing/page.js",
  "/settings/page": "app/settings/page.js",
  "/teacher/page": "app/teacher/page.js",
  "/test/page": "app/test/page.js"
}